yolosegment2labelme/__init__.py
yolosegment2labelme/polygon_saver.py
yolosegment2labelme/yolosegment2labelme.py
yolosegment2labelme-0.0.4.dist-info/LICENSE
yolosegment2labelme-0.0.4.dist-info/METADATA
yolosegment2labelme-0.0.4.dist-info/WHEEL
yolosegment2labelme-0.0.4.dist-info/entry_points.txt
yolosegment2labelme-0.0.4.dist-info/top_level.txt
yolosegment2labelme-0.0.4.dist-info/RECORD
