Metadata-Version: 2.1
Name: yolosegment2labelme
Version: 0.0.4
Summary: A small example package
Home-page: https://github.com/Abonia1/yolosegment2labelme
Download-URL: https://github.com/Abonia1/yolosegment2labelme/archive/refs/tags/v0.3.zip
Author: Abonia Sojasingarayar
Author-email: Abonia Sojasingarayar <aboniaa@gmail.com>
Project-URL: Homepage, https://github.com/Abonia1/yolosegment2labelme
Project-URL: Issues, https://github.com/Abonia1/yolosegment2labelme/issues
Keywords: python,yolo,segmentation,json,labelme,anylabeling
Classifier: Programming Language :: Python :: 3
Classifier: License :: OSI Approved :: MIT License
Classifier: Operating System :: OS Independent
Requires-Python: >=3.8
License-File: LICENSE
Requires-Dist: numpy
Requires-Dist: opencv-python
Requires-Dist: pillow
Requires-Dist: ultralytics
